odoo9_addon_stock_picking_tracking-9.0.1.0.0-py2.7-nspkg.pth
odoo9_addon_stock_picking_tracking-9.0.1.0.0.dist-info/DESCRIPTION.rst
odoo9_addon_stock_picking_tracking-9.0.1.0.0.dist-info/METADATA
odoo9_addon_stock_picking_tracking-9.0.1.0.0.dist-info/RECORD
odoo9_addon_stock_picking_tracking-9.0.1.0.0.dist-info/WHEEL
odoo9_addon_stock_picking_tracking-9.0.1.0.0.dist-info/metadata.json
odoo9_addon_stock_picking_tracking-9.0.1.0.0.dist-info/namespace_packages.txt
odoo9_addon_stock_picking_tracking-9.0.1.0.0.dist-info/top_level.txt
odoo_addons/stock_picking_tracking/README.rst
odoo_addons/stock_picking_tracking/__init__.py
odoo_addons/stock_picking_tracking/__openerp__.py
odoo_addons/stock_picking_tracking/demo/stock_tracking_demo.xml
odoo_addons/stock_picking_tracking/models/__init__.py
odoo_addons/stock_picking_tracking/models/stock_picking.py
odoo_addons/stock_picking_tracking/models/stock_picking_tracking_event.py
odoo_addons/stock_picking_tracking/models/stock_picking_tracking_group.py
odoo_addons/stock_picking_tracking/models/stock_picking_tracking_location.py
odoo_addons/stock_picking_tracking/security/ir.model.access.csv
odoo_addons/stock_picking_tracking/tests/__init__.py
odoo_addons/stock_picking_tracking/tests/common.py
odoo_addons/stock_picking_tracking/tests/test_stock_picking_tracking_event.py
odoo_addons/stock_picking_tracking/tests/test_stock_picking_tracking_group.py
odoo_addons/stock_picking_tracking/tests/test_stock_picking_tracking_location.py
odoo_addons/stock_picking_tracking/views/stock_menu.xml
odoo_addons/stock_picking_tracking/views/stock_picking_tracking_event_view.xml
odoo_addons/stock_picking_tracking/views/stock_picking_tracking_group_view.xml
odoo_addons/stock_picking_tracking/views/stock_picking_tracking_location_view.xml
odoo_addons/stock_picking_tracking/views/stock_picking_view.xml
