Metadata-Version: 2.0
Name: odoo9-addon-stock-picking-tracking
Version: 9.0.1.0.0
Summary: Adds a concept of event tracking for stock pickings
Home-page: https://laslabs.com/
Author: LasLabs
Author-email: UNKNOWN
License: LGPL-3
Platform: UNKNOWN
Classifier: Programming Language :: Python :: 2.7
Classifier: Framework :: Odoo
Classifier: License :: OSI Approved :: GNU Lesser General Public License v3 (LGPLv3)
Requires-Dist: odoo (<9.1a,>=9.0a)
